rtl/SPI_Master_MLF.v
// Model original: https://github.com/nandland/spi-master/tree/master/Verilog/source/SPI_Master.v
// el model que es presenta a continuació és una modificació del model original amb els requeriments establerts pels professors

module SPI_Master_MLF
    #(parameter SPI_MODE = 0,                                           //Determina quin model SPI utilitzem CPOL,CPHA: 0=00, 1=01, 2=10, 3=11
      parameter CLKS_PER_HALF_BIT = 2)                                  //Donada la freq de l'entrada (i_clk) determinem quants pulsos hi ha en mig bit (SPI_clk = 25MHz, i_clk= 100MHz; 100MHz/25MHz = 4 polsos / 2 = 2)
    (
        //Senyals de control
        input                   i_rst_n,                                //senyal de reset negada
        input                   i_clk,                                  //senyal del clock d'entrada

        //Senyals de TX (MOSI)
        input [7:0]             i_TX_Byte,                              //Byte que volem enviar des del SPI master   
        input                   i_TX_DV,                                //Pols d'un bit d'amplada que li diu al Master que miri i_TX_Byte i l'envii pel SPI TOP 
        output reg              o_TX_Ready,                             //Senyal que li diu al codi a mes alt nivell que esta preparat per una nova dada (i_TX_DV fa de trgger)

        //Senyals de RX (MISO)
        output reg              o_RX_DV,                                //Pols d'un bit que fa de trigger per enviar les dades per o_RX_Byte un cop siguin valides (r_RX_bit_count = 3'b000)
        output reg [7:0]        o_RX_Byte,                              //Dada convertida en paralel a partir de les dades en serie que arriben per MISO, indexat per r_RX_bit_Count

        //Senyals a TOP
        output reg              o_SPI_clk,                              //clock del nostre sistema SPI, es genera a partir de i_clk i s'ompla per r_SPI_clk
        input                   i_SPI_MISO,                             //senyal MISO que arriba en serie, la convertirem en un byte en paralel i l'enviarem per o_RX_Byte[7:0], o_RX_byte[r_RX_bit_count]
        output reg              o_SPI_MOSI                              //senyal MOSI que enviem a partir de o_TX_Ready, es controla a partir de r_TX_Byte[r_TX_bit_count]
    );      

    wire    w_CPOL;                                                     //Polaritat del clk
    wire    w_CPHA;                                                     //Fase del clk

    reg [4:0] r_SPI_clk_count;                                          //Conta per calcular el clock spi
    reg r_SPI_clk;                                                      //Registre on guardem el valor del clock spi
    reg [4:0] r_SPI_Clk_Edges;                                          //Numero de flancs en un byte (sempre 16, 1byte = 8bits; 1bit = 2 edges; 8bits = 16 edges)
    reg r_Leading_Edge;                                                 //registre on es guarda el flanc de pujada
    reg r_Trailing_Edge;                                                //registre on es guarda el flanc de baixada
    reg r_TX_DV;                                                        //registre on es guarda el valor de i_TX_DV
    reg [7:0] r_TX_Byte;                                                //registre on es guarda la dada de i__TX_byte i quan i_TX_DV s'activa l'envia

    reg[2:0] r_RX_Bit_Count;                                            //Registre que ens indica quin bit estem del byte Rx (111 -> 000)
    reg[2:0] r_TX_Bit_Count;                                            //registre que ens indica a quin bit estem del byte Tx (111 -> 000) 

    assign w_CPOL = (SPI_MODE == 2) | (SPI_MODE == 3);                  //Donem valor a la polaritat en funcio del mode que s'activa
    assign w_CPHA = (SPI_MODE == 1) | (SPI_MODE == 3);                  //Donem valor a la fase en funció del mode que s'activa

//Proposit: Generar el clock SPI el nombre correcte de cops

always @(posedge i_clk or negedge i_rst_n)
begin
    if(~i_rst_n)                                                        //en cas de reset tornem totes les variables a 0
    begin
        o_TX_Ready <= 1'b0;
        r_SPI_Clk_Edges <= 0;
        r_Leading_Edge <= 1'b0;
        r_Trailing_Edge <= 1'b0;
        r_SPI_clk <= w_CPOL;                                            //donem el valor de la polaritat per iniciar correctament
        r_SPI_clk_count <= 0; 
    end
    else
        begin
            r_Leading_Edge <= 1'b0;
            r_Trailing_Edge <= 1'b0;

            if (i_TX_DV)                                                    //Quan activem el trigger
            begin
                o_TX_Ready <= 1'b0;                                         //posem el bit a 0 per seguretat
                r_SPI_Clk_Edges <= 16;                                      //Posem 16 per generar 8 polsos de clk
            end
            else if (r_SPI_Clk_Edges > 0)                                   //Comencem a contar flancs per poder generar el clk de forma correcta
            begin
                o_TX_Ready <= 1'b0;                                     

                if(r_SPI_clk_count == CLKS_PER_HALF_BIT*2-1)                //flanc de pujada
                begin
                    r_SPI_Clk_Edges <= r_SPI_Clk_Edges - 5'b00001;
                    r_Trailing_Edge <= 1'b1;                            
                    r_SPI_clk_count <= 0;
                    r_SPI_clk <= ~r_SPI_clk;
                end
                else if (r_SPI_clk_count == CLKS_PER_HALF_BIT-1)            //flanc de baixada
                begin
                    r_SPI_Clk_Edges <= r_SPI_Clk_Edges - 5'b00001;
                    r_Leading_Edge <= 1'b1;
                    r_SPI_clk_count <= r_SPI_clk_count + 5'b00001;
                    r_SPI_clk <= ~r_SPI_clk;
                end
                else
                begin
                    r_SPI_clk_count <= r_SPI_clk_count + 5'b00001;                 //Un cop hem acabat la operació haurem generat un pols, per tant afegim 1 a la compta del clk
                end
            end
        else
        begin
            o_TX_Ready <= 1'b1;
        end
    end
end

//Proposit: Registra i_TX_Byte un cop DV s'activa, també guardem les dades de forma local en cas es canviin les dades al TOP
always @(posedge i_clk or negedge i_rst_n)
begin
    if(~i_rst_n)
    begin
        r_TX_Byte <= 8'h00; 
        r_TX_DV <= 1'b0;
    end
    else
    begin
        r_TX_DV <= i_TX_DV;                                             //delay d'un clock
        if(i_TX_DV)
        begin
            r_TX_Byte <= i_TX_Byte;                                         //utilitzem la dada que ens arriba des del TOP i la registrem localment
        end
    end
end

//Proposit: Generar les dades MOSI, funciona amb ambdues opcions de CPHA= 0 i CPHA = 1

always @(posedge i_clk or negedge i_rst_n)
begin
    if (~i_rst_n)                                                       //En el cas que s'activi el reset
    begin
        o_SPI_MOSI <= 1'b0;                                             //Posarem un 0 a la sortida
        r_TX_Bit_Count <= 3'b111;                                       //Donarem el valor maxim a tx count per enviar una nova dada correctament i en ordre
    end
    else
    begin
        if(o_TX_Ready)                                                  //En el cas que o tx ready estigui activa, el que significa que enviarem una trama
        begin
            r_TX_Bit_Count <= 3'b111;                                   //Li donem el valor maxim al comptador (conta de 111 -> 000)
        end

        else if (r_TX_DV & ~w_CPHA)                                     //Quan s'activi el trigger i estiguem en ordre amb el CPHA 
        begin
            o_SPI_MOSI <= r_TX_Byte[3'b111];                            //Enviem el primer byte per MOSI
            r_TX_Bit_Count <=3'b110;                                    //Disminuim el comptador
        end
        else if ((r_Leading_Edge & w_CPHA) | (r_Trailing_Edge & ~w_CPHA))   //Un cop alineat ja podem enviar tots els bits
        begin
            r_TX_Bit_Count <= r_TX_Bit_Count - 3'b001;                       
            o_SPI_MOSI <= r_TX_Byte[r_TX_Bit_Count];
        end
    end 
end

//Proposit: Llegir les dades MISO

always @(posedge i_clk or negedge i_rst_n)
begin
    if(~i_rst_n)                                                        //Si activem el reset
    begin
        o_RX_Byte <= 8'h00;                                             //RX byte torna a 0
        o_RX_DV <= 1'b0;                                                //Desactivem el trigger de rebuda
        r_RX_Bit_Count <= 3'b111;                                       //La conta torna al valor inicial
    end
    else
    begin
        o_RX_DV <= 1'b0;                                                //Mantenim el RX desactivat fins que acaem les operacions
        if(o_TX_Ready)                                                  //Si tenim les dades preparades
        begin
            r_RX_Bit_Count  <= 3'b111;                                  //La conta es posa al valor maxim
        end
        else if ((r_Leading_Edge & ~w_CPHA) | (r_Trailing_Edge & w_CPHA))   //Si estem alineats amb CPHA
        begin
            o_RX_Byte[r_RX_Bit_Count] <= i_SPI_MISO;                    //Comencem a rebre bits per MISO
            r_RX_Bit_Count <= r_RX_Bit_Count - 3'b001;                       //Disminuim la compta per indexar-ho de forma correcta
            if(r_RX_Bit_Count == 3'b000)                                //Un cop la compta ha acabat i vol dir que tot s'ha rebut amb exit
            begin
                o_RX_DV <= 1'b1;                                        //Activem el trigger
            end
        end
    end 
end

//Proposit: Afegir un delay al clock per poder alinear correctament les senyals

always @(posedge i_clk or negedge i_rst_n)
begin
    if(~i_rst_n)
    begin
        o_SPI_clk <= w_CPOL; 
    end
    else
    begin
        o_SPI_clk <= r_SPI_clk;
    end
end

endmodule

rtl/SPI_Master_MaquinaEstats_MLF.v
// Model original: https://github.com/nandland/spi-master/tree/master/Verilog/source/SPI_Master_With_Single_CS.v
// el model que es presenta a continuació és una modificació del model original amb els requeriments establerts pels professors

module SPI_Master_MaquinaEstats_MLF
 #(parameter SPI_MODE = 0,                                              //Determina quin model SPI utilitzem CPOL,CPHA: 0=00, 1=01, 2=10, 3=11
 parameter CLKS_PER_HALF_BIT = 2,                                       //Donada la freq de l'entrada (i_clk) determinem quants pulsos hi ha en mig bit (SPI_clk = 25MHz, i_clk= 100MHz; 100MHz/25MHz = 4 polsos / 2 = 2)
 parameter MAX_BYTES_PER_CS = 2,                                        //Numero de bytes que enviarem cada cop que s'activi el chip select
 parameter CS_INACTIVE_CLKS = 3)                                        //Determina el numero de cicles que ens mantindrem inactius un cop acabada la transmissio (necessari per alguns moduls)
 (
//Senyals de control
     input                                          i_rst_n,
     input                                          i_clk,
//Senyals de TX (MOSI)
     input [2:0]                                    i_TX_count,         //Variable que ens indicarà el numero de bytes que s'envien per TX
     input [7:0]                                    i_TX_Byte,
     input                                          i_TX_DV,
     output                                         o_TX_Ready,
//Senyals de RX (MISO)
     output reg [2:0]                               o_RX_count,         //Varialbe que ens idexiona les entrades de MISO en l'ordre correcte
     output                                         o_RX_DV,
     output [7:0]                                   o_RX_Byte,
//Senyals a top
     output                                         o_SPI_clk,
     input                                          i_SPI_MISO,
     output                                         o_SPI_MOSI,
     output                                         o_SPI_CS_n          //Sortida del CS cap a codi de mes alt nivell (TOP)
 );
//Definim els tres estats mitjançant un parametres local
 localparam                             IDLE = 2'b00;
 localparam                             TRANSFER = 2'b01;
 localparam                             CS_INACTIVE = 2'b10;
 
 reg[1:0]                               r_MaquinaEstats;                //En aquest registre guardarem l'estat en el qual ens trobem dins de la maquina d'estats
 reg                                    r_CS_n;                         //En aquest registre guardarem de forma local el vaor del CS
 reg [1:0]                              r_CS_Inactive_Count;            //Utilitzarem aquest registre per determinar els cicles que ens hem de mantindre amb CS inactius
 reg [2:0]                              r_TX_count;                     //Utilitzarem aquest registre per contar les dades que enviem per MOSI
 wire                                   w_Master_Ready;                 //Utilitzarem aquest wire per indicar quan el master està preparat per rebre una nova dada

 SPI_Master_MLF                                                         //Cridem el Master del SPI 
  #(.SPI_MODE(SPI_MODE),
    .CLKS_PER_HALF_BIT(CLKS_PER_HALF_BIT)
    ) SPI_Master_Inst
(
    //Senyals de control
    .i_rst_n(i_rst_n),
    .i_clk(i_clk),
    //Senyals de TX(MOSI)
    .i_TX_Byte(i_TX_Byte),
    .i_TX_DV(i_TX_DV),
    .o_TX_Ready(w_Master_Ready),
    //Senyals de RX(MISO)
    .o_RX_DV(o_RX_DV),
    .o_RX_Byte(o_RX_Byte),
    //Interficie SPI
    .o_SPI_clk(o_SPI_clk),
    .i_SPI_MISO(i_SPI_MISO),
    .o_SPI_MOSI(o_SPI_MOSI)
);

//Proposit: Controlar la senyal del CS a partir d'una maquina d'estats
 
always @(posedge i_clk or negedge i_rst_n)
begin
    if(~i_rst_n)                                                        //Si s'activa el reset 
    begin
        r_MaquinaEstats <= IDLE;                                        //Ens possisionem al estat incial IDLE
        r_CS_n <= 1'b1;                                                 //Desactivem el chip select
        r_TX_count <= 0;                                                //Reiniciem la compta de TX
        r_CS_Inactive_Count <= 2'b11;                                   //Donem el valor que haguem determinat al temps que haurem d'estar inacius
    end
    else
    begin
        case(r_MaquinaEstats)
        IDLE:                                                           //Estat inicial, esperem preparats per rebre una trama
            begin
               if(r_CS_n & i_TX_DV)                                     //Quan s'activa TX DV vol dir que alguna cosa arriba
               begin
                  r_TX_count <= i_TX_count -3'b001;                     //Comencem a contar enrere
                  r_CS_n <= 1'b0;                                       //Activem el Chip Select
                  r_MaquinaEstats <= TRANSFER;                          //Pasem al estat de transfer perque ja estem preparats per enviar
               end 
            end
        TRANSFER:                                                       //Estat de transferencia, ens trobem aqui quan estiguem enviant dades
            begin
               if(w_Master_Ready)                                       //En el cas que el master estigui preparat
               begin
                    if(r_TX_count > 0)                                  //Si la conta de TX es mes gran que 0
                    begin
                        if(i_TX_DV)                                     //I el trigger esta activat
                        begin
                        r_TX_count <= r_TX_count - 3'b001;              //Descontem un a la conta per passar a la seguent posicio
                        end
                    end
                    else
                    begin
                        r_CS_n <= 1'b1;                                 //Un cop TX count sigui 0, tornem a activar el CS
                        r_CS_Inactive_Count <= 2'b11;                   //Donem el valor maxim al temps que hem d'estar inactius
                        r_MaquinaEstats <= CS_INACTIVE;                 //Pasem al estat d'inactivitat
                    end
                end 
            end
        CS_INACTIVE:                                                    //Estat d'inactivitat, ens hem de trobar qui sempre i quan el modul que utilitzem requereixi d'un delay
            begin
                if(r_CS_Inactive_Count > 0)                             //Si el delay no es 0
                begin
                    r_CS_Inactive_Count <= r_CS_Inactive_Count - 1'b1;  //El fem decreixer fins arribar a 0
                end
                else
                begin
                    r_MaquinaEstats <= IDLE;                            //Un cop sigui 0 tornem a IDLE
                end
            end
        default:                                                        //En el cas d'error desactivarem el CS i tornarem a IDLE
            begin
               r_CS_n <= 1'b1;
               r_MaquinaEstats <=IDLE; 
            end
        endcase
    
    end 
end

//Proposit: Mantindre controlat RX count per poder indexar be les entrades 

always @(posedge i_clk)
begin
   begin
        if(r_CS_n)                                                      //En el cas que CS estigui actiu
        begin
        o_RX_count <= 0;                                                //Mantindrem la conta a 0 perque no arriba res
        end
        else if (o_RX_DV)                                               //Si s'activa el trigger d'entrada
        begin
            o_RX_count <= o_RX_count + 1'b1;                            //Incrementem el valor ja que ens estaran arribant nomes dades que depsres haurem d'indexar
        end
    end
end

 assign o_SPI_CS_n = r_CS_n;
 assign o_TX_Ready = ((r_MaquinaEstats == IDLE) | (r_MaquinaEstats == TRANSFER && w_Master_Ready == 1'b1 && r_TX_count > 0)) & ~i_TX_DV;


endmodule

tb/SPI_Master_MLF_CS_TB.v
//Model original: https:github.com/nandland/spi-master/blob/master/Verilog/sim/SPI_Master_With_Single_CS_TB.sv
//el model que es presenta a continuació és una modificació del model original amb els requeriments establerts pels professors

module SPI_MASTER_MLF_CS_TB();

    //Configurem els paràmetres en funció de la configuració que volguem aplicar al nostre test
    parameter SPI_MODE = 0;                                                   
    parameter CLKS_PER_HALF_BIT = 2;
    parameter MAIN_CLK_DELAY = 2;
    parameter MAX_BYTES_PER_CS = 2;
    parameter CS_INACTIVE_CLKS = 3;

    //Determinem els registres i wires que trobem al nostre test

    reg             r_rst_n = 1'b0;                                           
    reg             r_clk = 1'b0;
    reg             r_SPI_en = 1'b0;
    wire            w_SPI_clk;
    wire            w_SPI_CS_n;
    wire            w_SPI_MOSI;
    //wire            w_SPI_MISO;

    //Senyals especifiques del master

    reg[7:0]                                r_Master_TX_Byte = 0;
    reg                                     r_Master_TX_DV = 1'b0;
    wire                                    w_Master_TX_ready;
    wire                                    w_Master_RX_DV;
    wire[7:0]                               w_Master_RX_Byte;
    wire [2:0]                              w_Master_RX_count = 2'b10;
    wire [2:0]                              r_Master_TX_count = 2'b10;

    // Determinem la freüència del nostre rellotge

    always #(MAIN_CLK_DELAY) r_clk = ~r_clk;

    SPI_Master_MaquinaEstats_MLF
    #(.SPI_MODE(SPI_MODE),
      .CLKS_PER_HALF_BIT(CLKS_PER_HALF_BIT),
      .MAX_BYTES_PER_CS(MAX_BYTES_PER_CS),
      .CS_INACTIVE_CLKS(CS_INACTIVE_CLKS)
      ) UUT
    (
    
    //Senyals de control
      .i_rst_n(r_rst_n),
      .i_clk(r_clk),
    //Senyals TX(MOSI)
      .i_TX_count(r_Master_TX_count),
      .i_TX_Byte(r_Master_TX_Byte),
      .i_TX_DV(r_Master_TX_DV),
      .o_TX_Ready(w_Master_TX_ready),
    //Senyals RX(MISO)
      .o_RX_count(w_Master_RX_count),
      .o_RX_DV(w_Master_RX_DV),
      .o_RX_Byte(w_Master_RX_Byte),
    //Interficie SPI
      .o_SPI_clk(w_SPI_clk),
      .i_SPI_MISO(w_SPI_MOSI),                                                  //Senyals MISO y MOSI curtcircuitades per generar un echo
      .o_SPI_MOSI(w_SPI_MOSI),
      .o_SPI_CS_n(w_SPI_CS_n)
    );

    //Creem una tasca per enviar només un bit, utilitzarem un input de 8 bits el qual anomenem dades, d'aquesta manera podem enviar el byte que volguem (0x00 - 0xFF)

    task EnviaUnByte(input [7:0] dades);
    begin 
        @(posedge r_clk);
        r_Master_TX_Byte <= dades;                                              //Carreguem el byte al registre TX byte
        r_Master_TX_DV <= 1'b1;                                                 //Activem el bit DV 1 cicle de rellotge, el qual indica que les dàdes s'han carregat al registre
        @(posedge r_clk);
        r_Master_TX_DV <= 1'b0;
        @(posedge r_clk);
        @(posedge w_Master_TX_ready);
    end
    endtask

    initial
        begin
            $dumpfile("dump.vcd");
            $dumpvars;

            repeat(10) @(posedge r_clk);
            r_rst_n = 1'b0;                                                     //Reset inicial per configurar els valors inicials correctament
            repeat(10) @(posedge r_clk);
            r_rst_n = 1'b1;
            //envem dos bytes
            EnviaUnByte(8'h78);                                                 //Enviem un byte
            $display("He enviat el byte 0x78, Rebut 0x%X", w_Master_RX_Byte);   //Per consola comprovarem si s'ha enviat i rebut correctament
            #50
            EnviaUnByte(8'h9A);
            $display("He envial el byte 0x9A, Rebut 0x%X", w_Master_RX_Byte);

            repeat(100) @(posedge r_clk);
            $stop();       
        end
endmodule

sim/dump.vcd
$date
	Thu May 14 23:51:45 2020
$end
$version
	ModelSim Version 10.6d
$end
$timescale
	1ps
$end

$scope module SPI_MASTER_MLF_CS_TB $end
$var parameter 32 ! SPI_MODE $end
$var parameter 32 " CLKS_PER_HALF_BIT $end
$var parameter 32 # MAIN_CLK_DELAY $end
$var parameter 32 $ MAX_BYTES_PER_CS $end
$var parameter 32 % CS_INACTIVE_CLKS $end
$var reg 1 & r_rst_n $end
$var reg 1 ' r_clk $end
$var reg 1 ( r_SPI_en $end
$var wire 1 ) w_SPI_clk $end
$var wire 1 * w_SPI_CS_n $end
$var wire 1 + w_SPI_MOSI $end
$var reg 8 , r_Master_TX_Byte [7:0] $end
$var reg 1 - r_Master_TX_DV $end
$var wire 1 . w_Master_TX_ready $end
$var wire 1 / w_Master_RX_DV $end
$var wire 1 0 w_Master_RX_Byte [7] $end
$var wire 1 1 w_Master_RX_Byte [6] $end
$var wire 1 2 w_Master_RX_Byte [5] $end
$var wire 1 3 w_Master_RX_Byte [4] $end
$var wire 1 4 w_Master_RX_Byte [3] $end
$var wire 1 5 w_Master_RX_Byte [2] $end
$var wire 1 6 w_Master_RX_Byte [1] $end
$var wire 1 7 w_Master_RX_Byte [0] $end
$var wire 1 8 w_Master_RX_count [2] $end
$var wire 1 9 w_Master_RX_count [1] $end
$var wire 1 : w_Master_RX_count [0] $end
$var wire 1 ; r_Master_TX_count [2] $end
$var wire 1 < r_Master_TX_count [1] $end
$var wire 1 = r_Master_TX_count [0] $end

$scope task EnviaUnByte $end
$var reg 8 > dades [7:0] $end
$upscope $end

$scope module UUT $end
$var parameter 32 ? SPI_MODE $end
$var parameter 32 @ CLKS_PER_HALF_BIT $end
$var parameter 32 A MAX_BYTES_PER_CS $end
$var parameter 32 B CS_INACTIVE_CLKS $end
$var parameter 2 C IDLE $end
$var parameter 2 D TRANSFER $end
$var parameter 2 E CS_INACTIVE $end
$var wire 1 F i_rst_n $end
$var wire 1 G i_clk $end
$var wire 1 ; i_TX_count [2] $end
$var wire 1 < i_TX_count [1] $end
$var wire 1 = i_TX_count [0] $end
$var wire 1 H i_TX_Byte [7] $end
$var wire 1 I i_TX_Byte [6] $end
$var wire 1 J i_TX_Byte [5] $end
$var wire 1 K i_TX_Byte [4] $end
$var wire 1 L i_TX_Byte [3] $end
$var wire 1 M i_TX_Byte [2] $end
$var wire 1 N i_TX_Byte [1] $end
$var wire 1 O i_TX_Byte [0] $end
$var wire 1 P i_TX_DV $end
$var wire 1 . o_TX_Ready $end
$var reg 3 Q o_RX_count [2:0] $end
$var wire 1 / o_RX_DV $end
$var wire 1 0 o_RX_Byte [7] $end
$var wire 1 1 o_RX_Byte [6] $end
$var wire 1 2 o_RX_Byte [5] $end
$var wire 1 3 o_RX_Byte [4] $end
$var wire 1 4 o_RX_Byte [3] $end
$var wire 1 5 o_RX_Byte [2] $end
$var wire 1 6 o_RX_Byte [1] $end
$var wire 1 7 o_RX_Byte [0] $end
$var wire 1 ) o_SPI_clk $end
$var wire 1 + i_SPI_MISO $end
$var wire 1 + o_SPI_MOSI $end
$var wire 1 * o_SPI_CS_n $end
$var reg 2 R r_MaquinaEstats [1:0] $end
$var reg 1 S r_CS_n $end
$var reg 2 T r_CS_Inactive_Count [1:0] $end
$var reg 3 U r_TX_count [2:0] $end
$var wire 1 V w_Master_Ready $end

$scope module SPI_Master_Inst $end
$var parameter 32 W SPI_MODE $end
$var parameter 32 X CLKS_PER_HALF_BIT $end
$var wire 1 F i_rst_n $end
$var wire 1 G i_clk $end
$var wire 1 H i_TX_Byte [7] $end
$var wire 1 I i_TX_Byte [6] $end
$var wire 1 J i_TX_Byte [5] $end
$var wire 1 K i_TX_Byte [4] $end
$var wire 1 L i_TX_Byte [3] $end
$var wire 1 M i_TX_Byte [2] $end
$var wire 1 N i_TX_Byte [1] $end
$var wire 1 O i_TX_Byte [0] $end
$var wire 1 P i_TX_DV $end
$var reg 1 Y o_TX_Ready $end
$var reg 1 Z o_RX_DV $end
$var reg 8 [ o_RX_Byte [7:0] $end
$var reg 1 \ o_SPI_clk $end
$var wire 1 + i_SPI_MISO $end
$var reg 1 ] o_SPI_MOSI $end
$var wire 1 ^ w_CPOL $end
$var wire 1 _ w_CPHA $end
$var reg 5 ` r_SPI_clk_count [4:0] $end
$var reg 1 a r_SPI_clk $end
$var reg 5 b r_SPI_Clk_Edges [4:0] $end
$var reg 1 c r_Leading_Edge $end
$var reg 1 d r_Trailing_Edge $end
$var reg 1 e r_TX_DV $end
$var reg 8 f r_TX_Byte [7:0] $end
$var reg 3 g r_RX_Bit_Count [2:0] $end
$var reg 3 h r_TX_Bit_Count [2:0] $end
$upscope $end
$upscope $end
$upscope $end
$enddefinitions $end
#0
$dumpvars
0&
0'
0(
b0 ,
0-
bx Q
b0 R
1S
b11 T
b0 U
0Y
0Z
b0 [
0\
0]
b0 `
0a
b0 b
0c
0d
0e
b0 f
b111 g
b111 h
bx >
b0 !
b10 "
b10 #
b10 $
b11 %
b0 ?
b10 @
b10 A
b11 B
b0 C
b1 D
b10 E
b0 W
b10 X
0)
1*
0+
1.
0/
07
06
05
04
03
02
01
00
x:
x9
x8
0=
1<
0;
0V
0^
0_
0P
0O
0N
0M
0L
0K
0J
0I
0H
0G
0F
$end
#2
1'
1G
b0 Q
0:
08
#4
0'
0G
#6
1'
1G
#8
0'
0G
#10
1'
1G
#12
0'
0G
#14
1'
1G
#16
0'
0G
#18
1'
1G
#20
0'
0G
#22
1'
1G
#24
0'
0G
#26
1'
1G
#28
0'
0G
#30
1'
1G
#32
0'
0G
#34
1'
1G
#36
0'
0G
#38
1'
1G
#40
0'
0G
#42
1'
1G
#44
0'
0G
#46
1'
1G
#48
0'
0G
#50
1'
1G
#52
0'
0G
#54
1'
1G
#56
0'
0G
#58
1'
1G
#60
0'
0G
#62
1'
1G
#64
0'
0G
#66
1'
1G
#68
0'
0G
#70
1'
1G
#72
0'
0G
#74
1'
1G
#76
0'
0G
#78
1'
1G
1&
b1111000 >
1F
#80
0'
0G
#82
1'
1G
1Y
b1111000 ,
1-
1V
1L
1K
1J
1I
1P
0.
#84
0'
0G
#86
1'
1G
0Y
b10000 b
1e
b1111000 f
b1 U
0S
b1 R
0-
0V
0*
0P
#88
0'
0G
#90
1'
1G
b1 `
0e
b110 h
#92
0'
0G
#94
1'
1G
b1111 b
1c
b10 `
1a
#96
0'
0G
#98
1'
1G
0c
b11 `
b110 g
1\
1)
#100
0'
0G
#102
1'
1G
b1110 b
1d
b0 `
0a
#104
0'
0G
#106
1'
1G
0d
b1 `
b101 h
1]
0\
1+
0)
#108
0'
0G
#110
1'
1G
b1101 b
1c
b10 `
1a
#112
0'
0G
#114
1'
1G
0c
b11 `
b1000000 [
b101 g
1\
11
1)
#116
0'
0G
#118
1'
1G
b1100 b
1d
b0 `
0a
#120
0'
0G
#122
1'
1G
0d
b1 `
b100 h
0\
0)
#124
0'
0G
#126
1'
1G
b1011 b
1c
b10 `
1a
#128
0'
0G
#130
1'
1G
0c
b11 `
b1100000 [
b100 g
1\
12
1)
#132
0'
0G
#134
1'
1G
b1010 b
1d
b0 `
0a
#136
0'
0G
#138
1'
1G
0d
b1 `
b11 h
0\
0)
#140
0'
0G
#142
1'
1G
b1001 b
1c
b10 `
1a
#144
0'
0G
#146
1'
1G
0c
b11 `
b1110000 [
b11 g
1\
13
1)
#148
0'
0G
#150
1'
1G
b1000 b
1d
b0 `
0a
#152
0'
0G
#154
1'
1G
0d
b1 `
b10 h
0\
0)
#156
0'
0G
#158
1'
1G
b111 b
1c
b10 `
1a
#160
0'
0G
#162
1'
1G
0c
b11 `
b1111000 [
b10 g
1\
14
1)
#164
0'
0G
#166
1'
1G
b110 b
1d
b0 `
0a
#168
0'
0G
#170
1'
1G
0d
b1 `
b1 h
0]
0\
0+
0)
#172
0'
0G
#174
1'
1G
b101 b
1c
b10 `
1a
#176
0'
0G
#178
1'
1G
0c
b11 `
b1 g
1\
1)
#180
0'
0G
#182
1'
1G
b100 b
1d
b0 `
0a
#184
0'
0G
#186
1'
1G
0d
b1 `
b0 h
0\
0)
#188
0'
0G
#190
1'
1G
b11 b
1c
b10 `
1a
#192
0'
0G
#194
1'
1G
0c
b11 `
b0 g
1\
1)
#196
0'
0G
#198
1'
1G
b10 b
1d
b0 `
0a
#200
0'
0G
#202
1'
1G
0d
b1 `
b111 h
0\
0)
#204
0'
0G
#206
1'
1G
b1 b
1c
b10 `
1a
#208
0'
0G
#210
1'
1G
0c
b11 `
b111 g
1Z
1\
1/
1)
#212
0'
0G
#214
1'
1G
b0 b
1d
b0 `
0a
0Z
b1 Q
0/
x:
#216
0'
0G
#218
1'
1G
0d
1Y
b110 h
0\
1V
0)
1.
#220
0'
0G
#222
1'
1G
b111 h
#224
0'
0G
#226
1'
1G
#228
0'
0G
#230
1'
1G
#232
0'
0G
#234
1'
1G
#236
0'
0G
#238
1'
1G
#240
0'
0G
#242
1'
1G
#244
0'
0G
#246
1'
1G
#248
0'
0G
#250
1'
1G
#252
0'
0G
#254
1'
1G
#256
0'
0G
#258
1'
1G
#260
0'
0G
#262
1'
1G
#264
0'
0G
#266
1'
1G
#268
b10011010 >
0'
0G
#270
1'
1G
b10011010 ,
1-
1N
0J
0I
1H
1P
0.
#272
0'
0G
#274
1'
1G
0Y
b10000 b
1e
b10011010 f
b0 U
0-
0V
0P
#276
0'
0G
#278
1'
1G
b1 `
0e
1]
b110 h
1+
#280
0'
0G
#282
1'
1G
b1111 b
1c
b10 `
1a
#284
0'
0G
#286
1'
1G
0c
b11 `
b11111000 [
b110 g
1\
10
1)
#288
0'
0G
#290
1'
1G
b1110 b
1d
b0 `
0a
#292
0'
0G
#294
1'
1G
0d
b1 `
b101 h
0]
0\
0+
0)
#296
0'
0G
#298
1'
1G
b1101 b
1c
b10 `
1a
#300
0'
0G
#302
1'
1G
0c
b11 `
b10111000 [
b101 g
1\
01
1)
#304
0'
0G
#306
1'
1G
b1100 b
1d
b0 `
0a
#308
0'
0G
#310
1'
1G
0d
b1 `
b100 h
0\
0)
#312
0'
0G
#314
1'
1G
b1011 b
1c
b10 `
1a
#316
0'
0G
#318
1'
1G
0c
b11 `
b10011000 [
b100 g
1\
02
1)
#320
0'
0G
#322
1'
1G
b1010 b
1d
b0 `
0a
#324
0'
0G
#326
1'
1G
0d
b1 `
b11 h
1]
0\
1+
0)
#328
0'
0G
#330
1'
1G
b1001 b
1c
b10 `
1a
#332
0'
0G
#334
1'
1G
0c
b11 `
b11 g
1\
1)
#336
0'
0G
#338
1'
1G
b1000 b
1d
b0 `
0a
#340
0'
0G
#342
1'
1G
0d
b1 `
b10 h
0\
0)
#344
0'
0G
#346
1'
1G
b111 b
1c
b10 `
1a
#348
0'
0G
#350
1'
1G
0c
b11 `
b10 g
1\
1)
#352
0'
0G
#354
1'
1G
b110 b
1d
b0 `
0a
#356
0'
0G
#358
1'
1G
0d
b1 `
b1 h
0]
0\
0+
0)
#360
0'
0G
#362
1'
1G
b101 b
1c
b10 `
1a
#364
0'
0G
#366
1'
1G
0c
b11 `
b1 g
1\
1)
#368
0'
0G
#370
1'
1G
b100 b
1d
b0 `
0a
#372
0'
0G
#374
1'
1G
0d
b1 `
b0 h
1]
0\
1+
0)
#376
0'
0G
#378
1'
1G
b11 b
1c
b10 `
1a
#380
0'
0G
#382
1'
1G
0c
b11 `
b10011010 [
b0 g
1\
16
1)
#384
0'
0G
#386
1'
1G
b10 b
1d
b0 `
0a
#388
0'
0G
#390
1'
1G
0d
b1 `
b111 h
0]
0\
0+
0)
#392
0'
0G
#394
1'
1G
b1 b
1c
b10 `
1a
#396
0'
0G
#398
1'
1G
0c
b11 `
b111 g
1Z
1\
1/
1)
#400
0'
0G
#402
1'
1G
b0 b
1d
b0 `
0a
0Z
b10 Q
0/
0:
19
#404
0'
0G
#406
1'
1G
0d
1Y
b110 h
1]
0\
1V
1+
0)
#408
0'
0G
#410
1'
1G
b111 h
1S
b10 R
1*
#412
0'
0G
#414
1'
1G
b10 T
b0 Q
x9
#416
0'
0G
#418
1'
1G
b1 T
#420
0'
0G
#422
1'
1G
b0 T
#424
0'
0G
#426
1'
1G
b0 R
1.
